mapradar/__init__.py
mapradar/mapradar.cpython-312-darwin.so
mapradar-0.1.2.dist-info/METADATA
mapradar-0.1.2.dist-info/WHEEL
mapradar-0.1.2.dist-info/licenses/LICENSE
mapradar-0.1.2.dist-info/RECORD
