Metadata-Version: 2.4
Name: mapradar
Version: 0.1.2
Classifier: Development Status :: 4 - Beta
Classifier: Intended Audience :: Developers
Classifier: License :: OSI Approved :: MIT License
Classifier: Programming Language :: Python :: 3
Classifier: Programming Language :: Python :: 3.9
Classifier: Programming Language :: Python :: 3.10
Classifier: Programming Language :: Python :: 3.11
Classifier: Programming Language :: Python :: 3.12
Classifier: Programming Language :: Rust
License-File: LICENSE
Summary: Turn addresses into coordinates and find nearby amenities using Google Maps API
Keywords: geocoding,location,maps,places,google-maps
Author: iamprecieee
Requires-Python: >=3.9
Project-URL: Repository, https://github.com/iamprecieee/mapradar
